django_socio_grpc/__init__.py
django_socio_grpc/apps.py
django_socio_grpc/decorators.py
django_socio_grpc/exceptions.py
django_socio_grpc/filters.py
django_socio_grpc/generics.py
django_socio_grpc/grpc_actions/__init__.py
django_socio_grpc/grpc_actions/actions.py
django_socio_grpc/grpc_actions/placeholders.py
django_socio_grpc/grpc_actions/utils.py
django_socio_grpc/log.py
django_socio_grpc/management/__init__.py
django_socio_grpc/management/commands/__init__.py
django_socio_grpc/management/commands/generate_proto_old_way.py
django_socio_grpc/management/commands/generateproto.py
django_socio_grpc/management/commands/grpcrunaioserver.py
django_socio_grpc/management/commands/grpcrunserver.py
django_socio_grpc/middlewares.py
django_socio_grpc/mixins.py
django_socio_grpc/permissions.py
django_socio_grpc/proto_serializers.py
django_socio_grpc/protobuf/__init__.py
django_socio_grpc/protobuf/default_generated_data.py
django_socio_grpc/protobuf/exceptions.py
django_socio_grpc/protobuf/generation_plugin.py
django_socio_grpc/protobuf/generators.py
django_socio_grpc/protobuf/generators_old_way.py
django_socio_grpc/protobuf/json_format.py
django_socio_grpc/protobuf/message_name_constructor.py
django_socio_grpc/protobuf/proto_classes.py
django_socio_grpc/protobuf/protoparser/__init__.py
django_socio_grpc/protobuf/protoparser/protoparser.py
django_socio_grpc/protobuf/registry_singleton.py
django_socio_grpc/protobuf/typing.py
django_socio_grpc/request_transformer/__init__.py
django_socio_grpc/request_transformer/grpc_internal_container.py
django_socio_grpc/request_transformer/grpc_internal_proxy.py
django_socio_grpc/request_transformer/socio_internal_request.py
django_socio_grpc/request_transformer/socio_internal_response.py
django_socio_grpc/servicer_proxy.py
django_socio_grpc/services/__init__.py
django_socio_grpc/services/app_handler_registry.py
django_socio_grpc/services/base_service.py
django_socio_grpc/services/servicer_proxy.py
django_socio_grpc/settings.py
django_socio_grpc-0.25.0.dist-info/METADATA
django_socio_grpc-0.25.0.dist-info/WHEEL
django_socio_grpc-0.25.0.dist-info/entry_points.txt
django_socio_grpc-0.25.0.dist-info/licenses/LICENSE
django_socio_grpc-0.25.0.dist-info/RECORD
